cerina_foundry_mcp/__init__.py
cerina_foundry_mcp/config.py
cerina_foundry_mcp/server.py
cerina_foundry_mcp/api/__init__.py
cerina_foundry_mcp/api/client.py
cerina_foundry_mcp/api/types.py
cerina_foundry_mcp/tools/__init__.py
cerina_foundry_mcp/tools/approve.py
cerina_foundry_mcp/tools/create_exercise.py
cerina_foundry_mcp/tools/list_exercises.py
cerina_foundry_mcp/tools/session_status.py
cerina_mcp-0.1.1.dist-info/METADATA
cerina_mcp-0.1.1.dist-info/WHEEL
cerina_mcp-0.1.1.dist-info/entry_points.txt
cerina_mcp-0.1.1.dist-info/RECORD
