Metadata-Version: 2.4
Name: cerina-mcp
Version: 0.1.1
Summary: MCP server for CBT Clinical Review Multi-Agent System
Project-URL: Homepage, https://github.com/jagjeevan/cerina
Project-URL: Issues, https://github.com/jagjeevan/cerina/issues
Requires-Python: >=3.13
Requires-Dist: httpx>=0.27.0
Requires-Dist: mcp>=1.2.0
Requires-Dist: pydantic-settings>=2.0.0
Requires-Dist: pydantic>=2.9.0
Requires-Dist: python-dotenv>=1.0.0
